banner_nicou11/__init__.py
banner_nicou11/banner.py
banner_nicou11-0.5.1.dist-info/METADATA
banner_nicou11-0.5.1.dist-info/WHEEL
banner_nicou11-0.5.1.dist-info/entry_points.txt
banner_nicou11-0.5.1.dist-info/top_level.txt
banner_nicou11-0.5.1.dist-info/RECORD
