Metadata-Version: 2.1
Name: banner_nicou11
Version: 0.5.1
Summary: Default template for PDM package
Author-email: Nicou11 <lyoungin1204@gmail.com>
License: MIT
Project-URL: Homepage, https://github.com/nicou11/banner
Project-URL: Issues, https://github.com/nicou11/banner/issues
Requires-Python: ==3.11.*
Requires-Dist: pyfiglet >=1.0.2
